<InterfaceSummary>
<RtlPorts>
<name>gmem1</name>
<CType>
<TypeName>int</TypeName>
<TypeWidth>32</TypeWidth>
<PhysicalWidth>256</PhysicalWidth>
</CType>
<CFractionWidth>0</CFractionWidth>
<InvalidType>0</InvalidType>
</RtlPorts>
<RtlPorts>
<name>gmem0</name>
<CType>
<TypeName>ap_uint 256</TypeName>
<TypeWidth>256</TypeWidth>
<PhysicalWidth>256</PhysicalWidth>
</CType>
<CFractionWidth>0</CFractionWidth>
<InvalidType>0</InvalidType>
</RtlPorts>
<RtlPorts>
<name>width</name>
<CType>
<TypeName>unsigned int</TypeName>
<TypeWidth>32</TypeWidth>
<PhysicalWidth>32</PhysicalWidth>
</CType>
<CFractionWidth>0</CFractionWidth>
<InvalidType>0</InvalidType>
</RtlPorts>
<RtlPorts>
<name>height</name>
<CType>
<TypeName>unsigned int</TypeName>
<TypeWidth>32</TypeWidth>
<PhysicalWidth>32</PhysicalWidth>
</CType>
<CFractionWidth>0</CFractionWidth>
<InvalidType>0</InvalidType>
</RtlPorts>
<RtlPorts>
<name>stride</name>
<CType>
<TypeName>unsigned int</TypeName>
<TypeWidth>32</TypeWidth>
<PhysicalWidth>32</PhysicalWidth>
</CType>
<CFractionWidth>0</CFractionWidth>
<InvalidType>0</InvalidType>
</RtlPorts>
</InterfaceSummary>

